quantiphyse_datasim
